helloworld/__init__.py
helloworld/helloworld.py
helloworld_ajilraju-0.0.3.dist-info/LICENSE
helloworld_ajilraju-0.0.3.dist-info/METADATA
helloworld_ajilraju-0.0.3.dist-info/WHEEL
helloworld_ajilraju-0.0.3.dist-info/top_level.txt
helloworld_ajilraju-0.0.3.dist-info/RECORD
