Metadata-Version: 2.1
Name: helloworld-ajilraju
Version: 0.0.3
Summary: A package to print hello world
Home-page: https://github.com/ajilraju/pypa-helloworld
Author: Ajil Raju
Author-email: ajilraju01@gmail.com
License: UNKNOWN
Platform: UNKNOWN
Classifier: Programming Language :: Python :: 3
Classifier: License :: OSI Approved :: MIT License
Classifier: Operating System :: OS Independent
Requires-Python: >=3.6
